<chromosome id="3329" primary-parent-id="2012"><neuron id="0" type="in" activation="linear"/>
<neuron id="1" type="in" activation="linear"/>
<neuron id="2" type="in" activation="linear"/>
<neuron id="3" type="out" activation="sigmoid"/>
<connection id="4" src-id="0" dest-id="3" weight="-7.170826392764695"/>
<connection id="5" src-id="1" dest-id="3" weight="5.042264784037129"/>
<connection id="6" src-id="2" dest-id="3" weight="4.810720764800044"/>
<neuron id="296" type="hid" activation="sigmoid"/>
<connection id="298" src-id="296" dest-id="3" weight="-8.635773065433641"/>
<neuron id="566" type="hid" activation="sigmoid"/>
<connection id="567" src-id="2" dest-id="566" weight="4.676722071635233"/>
<connection id="568" src-id="566" dest-id="296" weight="0.9369163515435828"/>
<connection id="695" src-id="0" dest-id="566" weight="0.08689259566460944"/>
<connection id="1090" src-id="1" dest-id="566" weight="-0.20410943533935466"/>
</chromosome>